README.rst
asterisk_plus_agent.py
setup.py
asterisk_plus_agent_test.egg-info/PKG-INFO
asterisk_plus_agent_test.egg-info/SOURCES.txt
asterisk_plus_agent_test.egg-info/dependency_links.txt
asterisk_plus_agent_test.egg-info/entry_points.txt
asterisk_plus_agent_test.egg-info/not-zip-safe
asterisk_plus_agent_test.egg-info/requires.txt
asterisk_plus_agent_test.egg-info/top_level.txt