Metadata-Version: 2.1
Name: asterisk-plus-agent-test
Version: 1.0
Summary: Asterisk Plus PBX Agent
Home-page: https://odoopbx.com
Author: Odooist
Author-email: odooist@gmail.com
License: Odoo Enterprise Edition License v1.0
Platform: UNKNOWN
Classifier: Development Status :: 5 - Production/Stable
Classifier: Intended Audience :: Developers
Classifier: Topic :: Software Development :: Build Tools
Classifier: License :: OSI Approved :: MIT License
Classifier: Programming Language :: Python :: 3.10
